problem_builder/__init__.py
problem_builder/answer.py
problem_builder/choice.py
problem_builder/completion.py
problem_builder/dashboard.py
problem_builder/dashboard_visual.py
problem_builder/instructor_tool.py
problem_builder/mcq.py
problem_builder/mentoring.py
problem_builder/message.py
problem_builder/mixins.py
problem_builder/models.py
problem_builder/mrq.py
problem_builder/platform_dependencies.py
problem_builder/plot.py
problem_builder/questionnaire.py
problem_builder/settings.py
problem_builder/slider.py
problem_builder/step.py
problem_builder/step_review.py
problem_builder/sub_api.py
problem_builder/swipe.py
problem_builder/table.py
problem_builder/tasks.py
problem_builder/tip.py
problem_builder/utils.py
problem_builder/management/__init__.py
problem_builder/management/commands/__init__.py
problem_builder/management/commands/copy_deprecated_course_id.py
problem_builder/migrations/0001_initial.py
problem_builder/migrations/0002_auto_20160121_1525.py
problem_builder/migrations/0003_auto_20161124_0755.py
problem_builder/migrations/0004_copy_course_ids.py
problem_builder/migrations/0005_auto_20170112_1021.py
problem_builder/migrations/0006_remove_deprecated_course_id.py
problem_builder/migrations/0007_lengthen_student_id_field.py
problem_builder/migrations/__init__.py
problem_builder/public/css/answer.css
problem_builder/public/css/dashboard.css
problem_builder/public/css/instructor_tool.css
problem_builder/public/css/mentoring-table.css
problem_builder/public/css/overlay.css
problem_builder/public/css/plot-preview.css
problem_builder/public/css/plot.css
problem_builder/public/css/problem-builder-edit.css
problem_builder/public/css/problem-builder-tinymce-content.css
problem_builder/public/css/problem-builder.css
problem_builder/public/css/questionnaire-edit.css
problem_builder/public/css/questionnaire.css
problem_builder/public/img/immunity-map-assumptions-bg.png
problem_builder/public/img/immunity-map-bg.png
problem_builder/public/js/answer.js
xblock_problem_builder-5.2.0.dist-info/licenses/AUTHORS
xblock_problem_builder-5.2.0.dist-info/licenses/LICENSE
xblock_problem_builder-5.2.0.dist-info/licenses/LICENSE.MIT
xblock_problem_builder-5.2.0.dist-info/METADATA
xblock_problem_builder-5.2.0.dist-info/WHEEL
xblock_problem_builder-5.2.0.dist-info/entry_points.txt
xblock_problem_builder-5.2.0.dist-info/top_level.txt
xblock_problem_builder-5.2.0.dist-info/RECORD
