Metadata-Version: 2.4
Name: xblock-problem-builder
Version: 5.2.0
Summary: XBlock - Problem Builder
Home-page: https://github.com/open-craft/problem-builder
Author: OpenCraft
License: AGPL v3
Keywords: Python edx
Requires-Python: >=3.11
License-File: LICENSE
License-File: LICENSE.MIT
License-File: AUTHORS
Requires-Dist: Django
Requires-Dist: edx-opaque-keys
Requires-Dist: xblock-utils
Dynamic: author
Dynamic: description
Dynamic: description-content-type
Dynamic: home-page
Dynamic: keywords
Dynamic: license
Dynamic: license-file
Dynamic: requires-dist
Dynamic: requires-python
Dynamic: summary
